nse_workday/__init__.py
nse_workday/__init__.pyi
nse_workday/exclist.d
nse_workday/hlist.d
nse_workday/nse_workday.py
nse_workday/nse_workday.pyi
nse_workday/py.typed
nse_workday-0.0.9.dist-info/METADATA
nse_workday-0.0.9.dist-info/WHEEL
nse_workday-0.0.9.dist-info/top_level.txt
nse_workday-0.0.9.dist-info/RECORD
