Metadata-Version: 2.4
Name: nse_workday
Version: 0.0.9
Summary: For Calculating days based on NSE Holidays(2010-2025)
Home-page: https://github.com/Tapanhaz/nse_workday
Author: Tapan Hazarika
Dynamic: author
Dynamic: description
Dynamic: description-content-type
Dynamic: home-page
Dynamic: summary
